setup.py
dl_package/__init__.py
dl_package/dl_codes.py
dl_package.egg-info/PKG-INFO
dl_package.egg-info/SOURCES.txt
dl_package.egg-info/dependency_links.txt
dl_package.egg-info/top_level.txt