Metadata-Version: 2.1
Name: dl-package
Version: 1.0.0
Summary: dl_codes
Author: geekaman22july
Author-email: geekaman22july@gmail.com
